[
	{
		"fileName": "../../hp/hp181231.mp3"
	},
	{
		"fileName": "../../sa/sa181231.mp3"
	},
	{
		"fileName": "../../ka/ka181231.mp3"
	},
	{
		"fileName": "../../fc/fc181231.mp3"
	},
	{
		"fileName": "../../yu/yu181231.mp3"
	},
	{
		"fileName": "../../bc/bc181231.mp3"
	},
	{
		"fileName": "../../ir/ir181231.mp3"
	},
	{
		"fileName": "../../im/im181231.mp3"
	},
	{
		"fileName": "../../cc/cc181231.mp3"
	},
	{
		"fileName": "../../ib/ib181231.mp3"
	},
	{
		"fileName": "../../pc/pc181231.mp3"
	},
	{
		"fileName": "../../ut/ut181231.mp3"
	},
	{
		"fileName": "../../se/se181231.mp3"
	},
	{
		"fileName": "../../up/up181231.mp3"
	},
	{
		"fileName": "../../hg/hg181231.mp3"
	},
	{
		"fileName": "../../wf/wf181231.mp3"
	},
	{
		"fileName": "../../dy/dy181231.mp3"
	},
	{
		"fileName": "../../tg/tg181231.mp3"
	},
	{
		"fileName": "../../gn/gn181231.mp3"
	},
	{
		"fileName": "../../ee/ee181231.mp3"
	}
]